ethel/__init__.py
ethel/account.py
ethel/api/__init__.py
ethel/api/base.py
ethel/api/candlepin.py
ethel/api/exceptions.py
ethel/api/payloads/pool.yml
ethel/api/payloads/user.yml
ethel/api/payloads/user_v2.yml
ethel/api/subscription.py
ethel/api/terms.py
ethel/api/user.py
ethel/api/utils.py
ethel/ethel.py
ethel/utils.py
ethel-3.0.0rc2.dist-info/LICENSE
ethel-3.0.0rc2.dist-info/WHEEL
ethel-3.0.0rc2.dist-info/METADATA
ethel-3.0.0rc2.dist-info/RECORD
