Metadata-Version: 2.1
Name: ethel
Version: 3.0.0rc2
Summary: Account Management Tool for Testing
Home-page: https://github.com/tumido/ethel
License: MIT
Keywords: testing-tool,account-management,candlepin
Author: Tomas Coufal
Author-email: tcoufal@redhat.com
Maintainer: Tomas Coufal
Maintainer-email: tcoufal@redhat.com
Requires-Python: >=3.7,<4.0
Classifier: Intended Audience :: Developers
Classifier: License :: OSI Approved :: MIT License
Classifier: Programming Language :: Python :: 3
Classifier: Programming Language :: Python :: 3.7
Classifier: Programming Language :: Python :: 3.8
Classifier: Topic :: Software Development :: Libraries :: Python Modules
Classifier: Topic :: Software Development :: Testing
Requires-Dist: Jinja2
Requires-Dist: pyyaml
Requires-Dist: requests
Project-URL: Repository, https://github.com/tumido/ethel
